battlesimulation/__init__.py
battlesimulation/__main__.py
battlesimulation/battle_simulation.py
battlesimulation/context.py
battlesimulation/data.json
battlesimulation/components/__init__.py
battlesimulation/components/basic_game_entity.py
battlesimulation/components/building.py
battlesimulation/components/config.py
battlesimulation/components/damage.py
battlesimulation/components/module_and_bonuses.py
battlesimulation/components/planet.py
battlesimulation/components/rocket.py
battlesimulation/components/spacefleet.py
battlesimulation/components/spaceship.py
battlesimulation/components/utility.py
galaxy_online_battle_simulation-1.2.0.dist-info/LICENSE
galaxy_online_battle_simulation-1.2.0.dist-info/METADATA
galaxy_online_battle_simulation-1.2.0.dist-info/WHEEL
galaxy_online_battle_simulation-1.2.0.dist-info/entry_points.txt
galaxy_online_battle_simulation-1.2.0.dist-info/top_level.txt
galaxy_online_battle_simulation-1.2.0.dist-info/RECORD
