Metadata-Version: 2.1
Name: galaxy-online-battle-simulation
Version: 1.2.0
Summary: Module for simulation of different battles in the online space strategy game Galaxy Online.
Author: fadedness
License: The MIT License (MIT)
Project-URL: Homepage, https://github.com/fadedness/galaxy-online-battle-simulation
Keywords: galaxy,online,battle,simulation
Classifier: License :: OSI Approved :: MIT License
Classifier: Programming Language :: Python
Classifier: Programming Language :: Python :: 3
Requires-Python: >=3.7
License-File: LICENSE
